geosuntransformlib/__init__.py
geosuntransformlib/geosunTransformLib.py
geosuntransformlib/py.typed
geosuntransformlib-0.0.1.dist-info/METADATA
geosuntransformlib-0.0.1.dist-info/WHEEL
geosuntransformlib-0.0.1.dist-info/top_level.txt
geosuntransformlib-0.0.1.dist-info/RECORD
